Metadata-Version: 2.1
Name: auth-swust
Version: 1.5.0
Summary: 模拟登录西南科技大学一站式网上服务大厅，带验证码识别
Home-page: https://github.com/BuddingLab/auth_swust
Author: BudyLab
Author-email: admin@maxlv.org
License: UNKNOWN
Platform: UNKNOWN
Classifier: Programming Language :: Python :: 3.6
Classifier: Programming Language :: Python :: 3.7
Classifier: License :: OSI Approved :: MIT License
Classifier: Operating System :: OS Independent
Requires-Dist: beautifulsoup4
Requires-Dist: lxml
Requires-Dist: Pillow
Requires-Dist: requests
Requires-Dist: scikit-image
Requires-Dist: pytest
Requires-Dist: loguru
